[
    {
        "link": "https://github.com/Felixelpapu25/prueb2024/archive/refs/heads/main.zip",
        "min_version": "0.2F",
        "recommended": "",
        "modpack": "freeXpansion",
        "logo": "https://raw.githubusercontent.com/Felixelpapu25/insaneVersion/main/expasion.png",
        "author": "insaneTeam",
        "fileName": "freeXpansion.zip",
        "updated": "FreePlay bonusSongs"
    },

    {
        "link": "https://gamebanana.com/dl/1240467",
        "modpack": "isaBmUpdate",
        "min_version": "0.2.5",
        "recommended": "",
        "logo": "https://raw.githubusercontent.com/Felixelpapu25/insaneVersion/main/update.png",
        "author": "",
        "fileName": "isaBm.zip",
        "updated": "IsaBm update"
    },
       {
        "link": "https://github.com/FelixGsf/BSW1/releases/download/W1BS/BSW1.zip",
        "modpack": "Week1 Shaders!",
        "min_version": "3.4F",
        "recommended": "YES",
        "logo": "https://raw.githubusercontent.com/Felixelpapu25/insaneVersion/main/update.png",
        "author": "Sax_sh3",
        "fileName": "isaBm.zip",
        "updated": "BW1S"
    }
]
